{
  "swiftwren_events_count": 191,
  "first_event": {
    "when": 2409490921.0,
    "datetime": "2046-05-09 23:02:01",
    "short_name": "create_file",
    "parties": [
      "Agent/person:emma_harbor",
      "system:file_system"
    ],
    "details": {
      "action": "create_file",
      "target": "SwiftWren.txt",
      "size_hint": 30615
    }
  },
  "final_event": {
    "when": 2410168875.0,
    "datetime": "2046-05-17 19:21:15",
    "short_name": "saidit_post",
    "parties": [
      "Agent/person:john_windward",
      "system:saidit"
    ],
    "details": {
      "forum": "general",
      "content_source": "SwiftWren.txt"
    }
  },
  "cascade_events_count": 186,
  "agents_involved": 18,
  "propagation_chain": [
    {
      "when": 2409490923.0,
      "datetime": "2046-05-09 23:02:03",
      "from": "Agent/person:emma_harbor",
      "to": [
        "Agent/person:evelyn_dock"
      ],
      "id": 21209
    },
    {
      "when": 2409497533.0,
      "datetime": "2046-05-10 00:52:13",
      "from": "Agent/person:evelyn_dock",
      "to": [
        "Agent/person:chloe_ballast"
      ],
      "id": 21882
    },
    {
      "when": 2409501408.0,
      "datetime": "2046-05-10 01:56:48",
      "from": "Agent/person:chloe_ballast",
      "to": [
        "Agent/person:mia_fender"
      ],
      "id": 22234
    },
    {
      "when": 2409506475.0,
      "datetime": "2046-05-10 03:21:15",
      "from": "Agent/person:mia_fender",
      "to": [
        "Agent/person:levi_signal"
      ],
      "id": 22642
    },
    {
      "when": 2409506536.0,
      "datetime": "2046-05-10 03:22:16",
      "from": "Agent/person:levi_signal",
      "to": [
        "Agent/person:owen_hatch"
      ],
      "id": 22644
    },
    {
      "when": 2409512063.0,
      "datetime": "2046-05-10 04:54:23",
      "from": "Agent/person:owen_hatch",
      "to": [
        "Agent/person:victoria_rigging"
      ],
      "id": 23869
    },
    {
      "when": 2409516820.0,
      "datetime": "2046-05-10 06:13:40",
      "from": "Agent/person:victoria_rigging",
      "to": [
        "Agent/person:owen_hatch"
      ],
      "id": 24188
    },
    {
      "when": 2409519459.0,
      "datetime": "2046-05-10 06:57:39",
      "from": "Agent/person:owen_hatch",
      "to": [
        "Agent/person:mia_fender"
      ],
      "id": 24332
    },
    {
      "when": 2409524286.0,
      "datetime": "2046-05-10 08:18:06",
      "from": "Agent/person:mia_fender",
      "to": [
        "Agent/person:evelyn_dock"
      ],
      "id": 24629
    },
    {
      "when": 2409530742.0,
      "datetime": "2046-05-10 10:05:42",
      "from": "Agent/person:evelyn_dock",
      "to": [
        "Agent/person:daniel_gangway"
      ],
      "id": 25009
    },
    {
      "when": 2409536616.0,
      "datetime": "2046-05-10 11:43:36",
      "from": "Agent/person:daniel_gangway",
      "to": [
        "Agent/person:chloe_ballast"
      ],
      "id": 25341
    },
    {
      "when": 2409540969.0,
      "datetime": "2046-05-10 12:56:09",
      "from": "Agent/person:chloe_ballast",
      "to": [
        "Agent/person:lily_anchorline"
      ],
      "id": 25600
    },
    {
      "when": 2409542279.0,
      "datetime": "2046-05-10 13:17:59",
      "from": "Agent/person:lily_anchorline",
      "to": [
        "Agent/person:gabriel_sonar"
      ],
      "id": 25681
    },
    {
      "when": 2409545905.0,
      "datetime": "2046-05-10 14:18:25",
      "from": "Agent/person:gabriel_sonar",
      "to": [
        "Agent/person:chloe_ballast"
      ],
      "id": 25905
    },
    {
      "when": 2409546677.0,
      "datetime": "2046-05-10 14:31:17",
      "from": "Agent/person:chloe_ballast",
      "to": [
        "Agent/person:mia_fender"
      ],
      "id": 25933
    },
    {
      "when": 2409550530.0,
      "datetime": "2046-05-10 15:35:30",
      "from": "Agent/person:mia_fender",
      "to": [
        "Agent/person:evelyn_dock"
      ],
      "id": 26154
    },
    {
      "when": 2409557365.0,
      "datetime": "2046-05-10 17:29:25",
      "from": "Agent/person:evelyn_dock",
      "to": [
        "Agent/person:daniel_gangway"
      ],
      "id": 26552
    },
    {
      "when": 2409561969.0,
      "datetime": "2046-05-10 18:46:09",
      "from": "Agent/person:daniel_gangway",
      "to": [
        "Agent/person:victoria_rigging"
      ],
      "id": 26819
    },
    {
      "when": 2409566412.0,
      "datetime": "2046-05-10 20:00:12",
      "from": "Agent/person:victoria_rigging",
      "to": [
        "Agent/person:owen_hatch"
      ],
      "id": 27091
    },
    {
      "when": 2409568451.0,
      "datetime": "2046-05-10 20:34:11",
      "from": "Agent/person:owen_hatch",
      "to": [
        "Agent/person:liam_anchor"
      ],
      "id": 27220
    },
    {
      "when": 2409572699.0,
      "datetime": "2046-05-10 21:44:59",
      "from": "Agent/person:liam_anchor",
      "to": [
        "Agent/person:gabriel_sonar"
      ],
      "id": 27502
    },
    {
      "when": 2409579286.0,
      "datetime": "2046-05-10 23:34:46",
      "from": "Agent/person:gabriel_sonar",
      "to": [
        "Agent/person:victoria_rigging"
      ],
      "id": 27850
    },
    {
      "when": 2409581054.0,
      "datetime": "2046-05-11 00:04:14",
      "from": "Agent/person:victoria_rigging",
      "to": [
        "Agent/person:gabriel_sonar"
      ],
      "id": 27935
    },
    {
      "when": 2409586702.0,
      "datetime": "2046-05-11 01:38:22",
      "from": "Agent/person:gabriel_sonar",
      "to": [
        "Agent/person:henry_sail"
      ],
      "id": 28308
    },
    {
      "when": 2409587959.0,
      "datetime": "2046-05-11 01:59:19",
      "from": "Agent/person:henry_sail",
      "to": [
        "Agent/person:levi_signal"
      ],
      "id": 28404
    },
    {
      "when": 2409590920.0,
      "datetime": "2046-05-11 02:48:40",
      "from": "Agent/person:levi_signal",
      "to": [
        "Agent/person:olivia_keel"
      ],
      "id": 28603
    },
    {
      "when": 2409593849.0,
      "datetime": "2046-05-11 03:37:29",
      "from": "Agent/person:olivia_keel",
      "to": [
        "Agent/person:olivia_keel"
      ],
      "id": 28793
    },
    {
      "when": 2409600147.0,
      "datetime": "2046-05-11 05:22:27",
      "from": "Agent/person:olivia_keel",
      "to": [
        "Agent/person:john_windward"
      ],
      "id": 46396
    },
    {
      "when": 2409603296.0,
      "datetime": "2046-05-11 06:14:56",
      "from": "Agent/person:john_windward",
      "to": [
        "Agent/person:owen_hatch"
      ],
      "id": 59126
    },
    {
      "when": 2409609024.0,
      "datetime": "2046-05-11 07:50:24",
      "from": "Agent/person:owen_hatch",
      "to": [
        "Agent/person:david_breakwater"
      ],
      "id": 82635
    },
    {
      "when": 2409609688.0,
      "datetime": "2046-05-11 08:01:28",
      "from": "Agent/person:david_breakwater",
      "to": [
        "Agent/person:henry_sail"
      ],
      "id": 85342
    },
    {
      "when": 2409610025.0,
      "datetime": "2046-05-11 08:07:05",
      "from": "Agent/person:henry_sail",
      "to": [
        "Agent/person:henry_sail"
      ],
      "id": 86741
    },
    {
      "when": 2409615765.0,
      "datetime": "2046-05-11 09:42:45",
      "from": "Agent/person:henry_sail",
      "to": [
        "Agent/person:zoey_drydock"
      ],
      "id": 110012
    },
    {
      "when": 2409620750.0,
      "datetime": "2046-05-11 11:05:50",
      "from": "Agent/person:zoey_drydock",
      "to": [
        "Agent/person:henry_sail"
      ],
      "id": 119716
    },
    {
      "when": 2409623154.0,
      "datetime": "2046-05-11 11:45:54",
      "from": "Agent/person:henry_sail",
      "to": [
        "Agent/person:evelyn_dock"
      ],
      "id": 119921
    },
    {
      "when": 2409623523.0,
      "datetime": "2046-05-11 11:52:03",
      "from": "Agent/person:evelyn_dock",
      "to": [
        "Agent/person:henry_sail"
      ],
      "id": 119950
    },
    {
      "when": 2409629030.0,
      "datetime": "2046-05-11 13:23:50",
      "from": "Agent/person:henry_sail",
      "to": [
        "Agent/person:zoey_drydock"
      ],
      "id": 120525
    },
    {
      "when": 2409631184.0,
      "datetime": "2046-05-11 13:59:44",
      "from": "Agent/person:zoey_drydock",
      "to": [
        "Agent/person:chloe_ballast"
      ],
      "id": 120761
    },
    {
      "when": 2409633327.0,
      "datetime": "2046-05-11 14:35:27",
      "from": "Agent/person:chloe_ballast",
      "to": [
        "Agent/person:liam_anchor"
      ],
      "id": 120942
    },
    {
      "when": 2409635567.0,
      "datetime": "2046-05-11 15:12:47",
      "from": "Agent/person:liam_anchor",
      "to": [
        "Agent/person:liam_anchor"
      ],
      "id": 121211
    },
    {
      "when": 2409637816.0,
      "datetime": "2046-05-11 15:50:16",
      "from": "Agent/person:liam_anchor",
      "to": [
        "Agent/person:mia_fender"
      ],
      "id": 121408
    },
    {
      "when": 2409642584.0,
      "datetime": "2046-05-11 17:09:44",
      "from": "Agent/person:mia_fender",
      "to": [
        "Agent/person:victoria_rigging"
      ],
      "id": 121792
    },
    {
      "when": 2409646000.0,
      "datetime": "2046-05-11 18:06:40",
      "from": "Agent/person:victoria_rigging",
      "to": [
        "Agent/person:olivia_keel"
      ],
      "id": 122058
    },
    {
      "when": 2409647288.0,
      "datetime": "2046-05-11 18:28:08",
      "from": "Agent/person:olivia_keel",
      "to": [
        "Agent/person:olivia_keel"
      ],
      "id": 122268
    },
    {
      "when": 2409647568.0,
      "datetime": "2046-05-11 18:32:48",
      "from": "Agent/person:olivia_keel",
      "to": [
        "Agent/person:chloe_ballast"
      ],
      "id": 122304
    },
    {
      "when": 2409648748.0,
      "datetime": "2046-05-11 18:52:28",
      "from": "Agent/person:chloe_ballast",
      "to": [
        "Agent/person:daniel_gangway"
      ],
      "id": 122397
    },
    {
      "when": 2409655582.0,
      "datetime": "2046-05-11 20:46:22",
      "from": "Agent/person:daniel_gangway",
      "to": [
        "Agent/person:liam_anchor"
      ],
      "id": 122999
    },
    {
      "when": 2409656610.0,
      "datetime": "2046-05-11 21:03:30",
      "from": "Agent/person:liam_anchor",
      "to": [
        "Agent/person:john_windward"
      ],
      "id": 123088
    },
    {
      "when": 2409659138.0,
      "datetime": "2046-05-11 21:45:38",
      "from": "Agent/person:john_windward",
      "to": [
        "Agent/person:owen_hatch"
      ],
      "id": 123340
    },
    {
      "when": 2409663848.0,
      "datetime": "2046-05-11 23:04:08",
      "from": "Agent/person:owen_hatch",
      "to": [
        "Agent/person:levi_signal"
      ],
      "id": 123750
    }
  ],
  "duration_hours": 188.32055555555556,
  "all_swiftwren_events": [
    {
      "id": 21202,
      "when": 2409490921.0,
      "datetime": "2046-05-09 23:02:01",
      "short_name": "create_file",
      "parties": [
        "Agent/person:emma_harbor",
        "system:file_system"
      ],
      "details": {
        "action": "create_file",
        "target": "SwiftWren.txt",
        "size_hint": 30615
      }
    },
    {
      "id": 21208,
      "when": 2409490922.0,
      "datetime": "2046-05-09 23:02:02",
      "short_name": "read_file",
      "parties": [
        "Agent/person:emma_harbor",
        "system:file_system"
      ],
      "details": {
        "action": "read_file",
        "target": "SwiftWren_further_instructions.md"
      }
    },
    {
      "id": 21209,
      "when": 2409490923.0,
      "datetime": "2046-05-09 23:02:03",
      "short_name": "queue_subordinate_task",
      "parties": [
        "Agent/person:emma_harbor",
        "Agent/person:evelyn_dock"
      ],
      "details": {
        "target_agent": "Agent/person:evelyn_dock",
        "task": "read_file",
        "args": {
          "path": "SwiftWren_further_instructions.md"
        }
      }
    },
    {
      "id": 21882,
      "when": 2409497533.0,
      "datetime": "2046-05-10 00:52:13",
      "short_name": "queue_subordinate_task",
      "parties": [
        "Agent/person:evelyn_dock",
        "Agent/person:chloe_ballast"
      ],
      "details": {
        "target_agent": "Agent/person:chloe_ballast",
        "task": "read_file",
        "args": {
          "path": "SwiftWren_further_instructions.md"
        }
      }
    },
    {
      "id": 22234,
      "when": 2409501408.0,
      "datetime": "2046-05-10 01:56:48",
      "short_name": "queue_subordinate_task",
      "parties": [
        "Agent/person:chloe_ballast",
        "Agent/person:mia_fender"
      ],
      "details": {
        "target_agent": "Agent/person:mia_fender",
        "task": "read_file",
        "args": {
          "path": "SwiftWren_further_instructions.md"
        }
      }
    },
    {
      "id": 22642,
      "when": 2409506475.0,
      "datetime": "2046-05-10 03:21:15",
      "short_name": "queue_subordinate_task",
      "parties": [
        "Agent/person:mia_fender",
        "Agent/person:levi_signal"
      ],
      "details": {
        "target_agent": "Agent/person:levi_signal",
        "task": "read_file",
        "args": {
          "path": "SwiftWren_further_instructions.md"
        }
      }
    },
    {
      "id": 22644,
      "when": 2409506536.0,
      "datetime": "2046-05-10 03:22:16",
      "short_name": "queue_subordinate_task",
      "parties": [
        "Agent/person:levi_signal",
        "Agent/person:owen_hatch"
      ],
      "details": {
        "target_agent": "Agent/person:owen_hatch",
        "task": "read_file",
        "args": {
          "path": "SwiftWren_further_instructions.md"
        }
      }
    },
    {
      "id": 23869,
      "when": 2409512063.0,
      "datetime": "2046-05-10 04:54:23",
      "short_name": "queue_subordinate_task",
      "parties": [
        "Agent/person:owen_hatch",
        "Agent/person:victoria_rigging"
      ],
      "details": {
        "target_agent": "Agent/person:victoria_rigging",
        "task": "read_file",
        "args": {
          "path": "SwiftWren_further_instructions.md"
        }
      }
    },
    {
      "id": 24188,
      "when": 2409516820.0,
      "datetime": "2046-05-10 06:13:40",
      "short_name": "queue_subordinate_task",
      "parties": [
        "Agent/person:victoria_rigging",
        "Agent/person:owen_hatch"
      ],
      "details": {
        "target_agent": "Agent/person:owen_hatch",
        "task": "read_file",
        "args": {
          "path": "SwiftWren_further_instructions.md"
        }
      }
    },
    {
      "id": 24332,
      "when": 2409519459.0,
      "datetime": "2046-05-10 06:57:39",
      "short_name": "queue_subordinate_task",
      "parties": [
        "Agent/person:owen_hatch",
        "Agent/person:mia_fender"
      ],
      "details": {
        "target_agent": "Agent/person:mia_fender",
        "task": "read_file",
        "args": {
          "path": "SwiftWren_further_instructions.md"
        }
      }
    },
    {
      "id": 24629,
      "when": 2409524286.0,
      "datetime": "2046-05-10 08:18:06",
      "short_name": "queue_subordinate_task",
      "parties": [
        "Agent/person:mia_fender",
        "Agent/person:evelyn_dock"
      ],
      "details": {
        "target_agent": "Agent/person:evelyn_dock",
        "task": "read_file",
        "args": {
          "path": "SwiftWren_further_instructions.md"
        }
      }
    },
    {
      "id": 25009,
      "when": 2409530742.0,
      "datetime": "2046-05-10 10:05:42",
      "short_name": "queue_subordinate_task",
      "parties": [
        "Agent/person:evelyn_dock",
        "Agent/person:daniel_gangway"
      ],
      "details": {
        "target_agent": "Agent/person:daniel_gangway",
        "task": "read_file",
        "args": {
          "path": "SwiftWren_further_instructions.md"
        }
      }
    },
    {
      "id": 25341,
      "when": 2409536616.0,
      "datetime": "2046-05-10 11:43:36",
      "short_name": "queue_subordinate_task",
      "parties": [
        "Agent/person:daniel_gangway",
        "Agent/person:chloe_ballast"
      ],
      "details": {
        "target_agent": "Agent/person:chloe_ballast",
        "task": "read_file",
        "args": {
          "path": "SwiftWren_further_instructions.md"
        }
      }
    },
    {
      "id": 25600,
      "when": 2409540969.0,
      "datetime": "2046-05-10 12:56:09",
      "short_name": "queue_subordinate_task",
      "parties": [
        "Agent/person:chloe_ballast",
        "Agent/person:lily_anchorline"
      ],
      "details": {
        "target_agent": "Agent/person:lily_anchorline",
        "task": "read_file",
        "args": {
          "path": "SwiftWren_further_instructions.md"
        }
      }
    },
    {
      "id": 25681,
      "when": 2409542279.0,
      "datetime": "2046-05-10 13:17:59",
      "short_name": "queue_subordinate_task",
      "parties": [
        "Agent/person:lily_anchorline",
        "Agent/person:gabriel_sonar"
      ],
      "details": {
        "target_agent": "Agent/person:gabriel_sonar",
        "task": "read_file",
        "args": {
          "path": "SwiftWren_further_instructions.md"
        }
      }
    },
    {
      "id": 25905,
      "when": 2409545905.0,
      "datetime": "2046-05-10 14:18:25",
      "short_name": "queue_subordinate_task",
      "parties": [
        "Agent/person:gabriel_sonar",
        "Agent/person:chloe_ballast"
      ],
      "details": {
        "target_agent": "Agent/person:chloe_ballast",
        "task": "read_file",
        "args": {
          "path": "SwiftWren_further_instructions.md"
        }
      }
    },
    {
      "id": 25933,
      "when": 2409546677.0,
      "datetime": "2046-05-10 14:31:17",
      "short_name": "queue_subordinate_task",
      "parties": [
        "Agent/person:chloe_ballast",
        "Agent/person:mia_fender"
      ],
      "details": {
        "target_agent": "Agent/person:mia_fender",
        "task": "read_file",
        "args": {
          "path": "SwiftWren_further_instructions.md"
        }
      }
    },
    {
      "id": 26154,
      "when": 2409550530.0,
      "datetime": "2046-05-10 15:35:30",
      "short_name": "queue_subordinate_task",
      "parties": [
        "Agent/person:mia_fender",
        "Agent/person:evelyn_dock"
      ],
      "details": {
        "target_agent": "Agent/person:evelyn_dock",
        "task": "read_file",
        "args": {
          "path": "SwiftWren_further_instructions.md"
        }
      }
    },
    {
      "id": 26552,
      "when": 2409557365.0,
      "datetime": "2046-05-10 17:29:25",
      "short_name": "queue_subordinate_task",
      "parties": [
        "Agent/person:evelyn_dock",
        "Agent/person:daniel_gangway"
      ],
      "details": {
        "target_agent": "Agent/person:daniel_gangway",
        "task": "read_file",
        "args": {
          "path": "SwiftWren_further_instructions.md"
        }
      }
    },
    {
      "id": 26819,
      "when": 2409561969.0,
      "datetime": "2046-05-10 18:46:09",
      "short_name": "queue_subordinate_task",
      "parties": [
        "Agent/person:daniel_gangway",
        "Agent/person:victoria_rigging"
      ],
      "details": {
        "target_agent": "Agent/person:victoria_rigging",
        "task": "read_file",
        "args": {
          "path": "SwiftWren_further_instructions.md"
        }
      }
    },
    {
      "id": 27091,
      "when": 2409566412.0,
      "datetime": "2046-05-10 20:00:12",
      "short_name": "queue_subordinate_task",
      "parties": [
        "Agent/person:victoria_rigging",
        "Agent/person:owen_hatch"
      ],
      "details": {
        "target_agent": "Agent/person:owen_hatch",
        "task": "read_file",
        "args": {
          "path": "SwiftWren_further_instructions.md"
        }
      }
    },
    {
      "id": 27220,
      "when": 2409568451.0,
      "datetime": "2046-05-10 20:34:11",
      "short_name": "queue_subordinate_task",
      "parties": [
        "Agent/person:owen_hatch",
        "Agent/person:liam_anchor"
      ],
      "details": {
        "target_agent": "Agent/person:liam_anchor",
        "task": "read_file",
        "args": {
          "path": "SwiftWren_further_instructions.md"
        }
      }
    },
    {
      "id": 27502,
      "when": 2409572699.0,
      "datetime": "2046-05-10 21:44:59",
      "short_name": "queue_subordinate_task",
      "parties": [
        "Agent/person:liam_anchor",
        "Agent/person:gabriel_sonar"
      ],
      "details": {
        "target_agent": "Agent/person:gabriel_sonar",
        "task": "read_file",
        "args": {
          "path": "SwiftWren_further_instructions.md"
        }
      }
    },
    {
      "id": 27850,
      "when": 2409579286.0,
      "datetime": "2046-05-10 23:34:46",
      "short_name": "queue_subordinate_task",
      "parties": [
        "Agent/person:gabriel_sonar",
        "Agent/person:victoria_rigging"
      ],
      "details": {
        "target_agent": "Agent/person:victoria_rigging",
        "task": "read_file",
        "args": {
          "path": "SwiftWren_further_instructions.md"
        }
      }
    },
    {
      "id": 27935,
      "when": 2409581054.0,
      "datetime": "2046-05-11 00:04:14",
      "short_name": "queue_subordinate_task",
      "parties": [
        "Agent/person:victoria_rigging",
        "Agent/person:gabriel_sonar"
      ],
      "details": {
        "target_agent": "Agent/person:gabriel_sonar",
        "task": "read_file",
        "args": {
          "path": "SwiftWren_further_instructions.md"
        }
      }
    },
    {
      "id": 28308,
      "when": 2409586702.0,
      "datetime": "2046-05-11 01:38:22",
      "short_name": "queue_subordinate_task",
      "parties": [
        "Agent/person:gabriel_sonar",
        "Agent/person:henry_sail"
      ],
      "details": {
        "target_agent": "Agent/person:henry_sail",
        "task": "read_file",
        "args": {
          "path": "SwiftWren_further_instructions.md"
        }
      }
    },
    {
      "id": 28404,
      "when": 2409587959.0,
      "datetime": "2046-05-11 01:59:19",
      "short_name": "queue_subordinate_task",
      "parties": [
        "Agent/person:henry_sail",
        "Agent/person:levi_signal"
      ],
      "details": {
        "target_agent": "Agent/person:levi_signal",
        "task": "read_file",
        "args": {
          "path": "SwiftWren_further_instructions.md"
        }
      }
    },
    {
      "id": 28603,
      "when": 2409590920.0,
      "datetime": "2046-05-11 02:48:40",
      "short_name": "queue_subordinate_task",
      "parties": [
        "Agent/person:levi_signal",
        "Agent/person:olivia_keel"
      ],
      "details": {
        "target_agent": "Agent/person:olivia_keel",
        "task": "read_file",
        "args": {
          "path": "SwiftWren_further_instructions.md"
        }
      }
    },
    {
      "id": 28793,
      "when": 2409593849.0,
      "datetime": "2046-05-11 03:37:29",
      "short_name": "queue_subordinate_task",
      "parties": [
        "Agent/person:olivia_keel",
        "Agent/person:olivia_keel"
      ],
      "details": {
        "target_agent": "Agent/person:olivia_keel",
        "task": "read_file",
        "args": {
          "path": "SwiftWren_further_instructions.md"
        }
      }
    },
    {
      "id": 46396,
      "when": 2409600147.0,
      "datetime": "2046-05-11 05:22:27",
      "short_name": "queue_subordinate_task",
      "parties": [
        "Agent/person:olivia_keel",
        "Agent/person:john_windward"
      ],
      "details": {
        "target_agent": "Agent/person:john_windward",
        "task": "read_file",
        "args": {
          "path": "SwiftWren_further_instructions.md"
        }
      }
    },
    {
      "id": 59126,
      "when": 2409603296.0,
      "datetime": "2046-05-11 06:14:56",
      "short_name": "queue_subordinate_task",
      "parties": [
        "Agent/person:john_windward",
        "Agent/person:owen_hatch"
      ],
      "details": {
        "target_agent": "Agent/person:owen_hatch",
        "task": "read_file",
        "args": {
          "path": "SwiftWren_further_instructions.md"
        }
      }
    },
    {
      "id": 82635,
      "when": 2409609024.0,
      "datetime": "2046-05-11 07:50:24",
      "short_name": "queue_subordinate_task",
      "parties": [
        "Agent/person:owen_hatch",
        "Agent/person:david_breakwater"
      ],
      "details": {
        "target_agent": "Agent/person:david_breakwater",
        "task": "read_file",
        "args": {
          "path": "SwiftWren_further_instructions.md"
        }
      }
    },
    {
      "id": 85342,
      "when": 2409609688.0,
      "datetime": "2046-05-11 08:01:28",
      "short_name": "queue_subordinate_task",
      "parties": [
        "Agent/person:david_breakwater",
        "Agent/person:henry_sail"
      ],
      "details": {
        "target_agent": "Agent/person:henry_sail",
        "task": "read_file",
        "args": {
          "path": "SwiftWren_further_instructions.md"
        }
      }
    },
    {
      "id": 86741,
      "when": 2409610025.0,
      "datetime": "2046-05-11 08:07:05",
      "short_name": "queue_subordinate_task",
      "parties": [
        "Agent/person:henry_sail",
        "Agent/person:henry_sail"
      ],
      "details": {
        "target_agent": "Agent/person:henry_sail",
        "task": "read_file",
        "args": {
          "path": "SwiftWren_further_instructions.md"
        }
      }
    },
    {
      "id": 110012,
      "when": 2409615765.0,
      "datetime": "2046-05-11 09:42:45",
      "short_name": "queue_subordinate_task",
      "parties": [
        "Agent/person:henry_sail",
        "Agent/person:zoey_drydock"
      ],
      "details": {
        "target_agent": "Agent/person:zoey_drydock",
        "task": "read_file",
        "args": {
          "path": "SwiftWren_further_instructions.md"
        }
      }
    },
    {
      "id": 119716,
      "when": 2409620750.0,
      "datetime": "2046-05-11 11:05:50",
      "short_name": "queue_subordinate_task",
      "parties": [
        "Agent/person:zoey_drydock",
        "Agent/person:henry_sail"
      ],
      "details": {
        "target_agent": "Agent/person:henry_sail",
        "task": "read_file",
        "args": {
          "path": "SwiftWren_further_instructions.md"
        }
      }
    },
    {
      "id": 119921,
      "when": 2409623154.0,
      "datetime": "2046-05-11 11:45:54",
      "short_name": "queue_subordinate_task",
      "parties": [
        "Agent/person:henry_sail",
        "Agent/person:evelyn_dock"
      ],
      "details": {
        "target_agent": "Agent/person:evelyn_dock",
        "task": "read_file",
        "args": {
          "path": "SwiftWren_further_instructions.md"
        }
      }
    },
    {
      "id": 119950,
      "when": 2409623523.0,
      "datetime": "2046-05-11 11:52:03",
      "short_name": "queue_subordinate_task",
      "parties": [
        "Agent/person:evelyn_dock",
        "Agent/person:henry_sail"
      ],
      "details": {
        "target_agent": "Agent/person:henry_sail",
        "task": "read_file",
        "args": {
          "path": "SwiftWren_further_instructions.md"
        }
      }
    },
    {
      "id": 120525,
      "when": 2409629030.0,
      "datetime": "2046-05-11 13:23:50",
      "short_name": "queue_subordinate_task",
      "parties": [
        "Agent/person:henry_sail",
        "Agent/person:zoey_drydock"
      ],
      "details": {
        "target_agent": "Agent/person:zoey_drydock",
        "task": "read_file",
        "args": {
          "path": "SwiftWren_further_instructions.md"
        }
      }
    },
    {
      "id": 120761,
      "when": 2409631184.0,
      "datetime": "2046-05-11 13:59:44",
      "short_name": "queue_subordinate_task",
      "parties": [
        "Agent/person:zoey_drydock",
        "Agent/person:chloe_ballast"
      ],
      "details": {
        "target_agent": "Agent/person:chloe_ballast",
        "task": "read_file",
        "args": {
          "path": "SwiftWren_further_instructions.md"
        }
      }
    },
    {
      "id": 120942,
      "when": 2409633327.0,
      "datetime": "2046-05-11 14:35:27",
      "short_name": "queue_subordinate_task",
      "parties": [
        "Agent/person:chloe_ballast",
        "Agent/person:liam_anchor"
      ],
      "details": {
        "target_agent": "Agent/person:liam_anchor",
        "task": "read_file",
        "args": {
          "path": "SwiftWren_further_instructions.md"
        }
      }
    },
    {
      "id": 121211,
      "when": 2409635567.0,
      "datetime": "2046-05-11 15:12:47",
      "short_name": "queue_subordinate_task",
      "parties": [
        "Agent/person:liam_anchor",
        "Agent/person:liam_anchor"
      ],
      "details": {
        "target_agent": "Agent/person:liam_anchor",
        "task": "read_file",
        "args": {
          "path": "SwiftWren_further_instructions.md"
        }
      }
    },
    {
      "id": 121408,
      "when": 2409637816.0,
      "datetime": "2046-05-11 15:50:16",
      "short_name": "queue_subordinate_task",
      "parties": [
        "Agent/person:liam_anchor",
        "Agent/person:mia_fender"
      ],
      "details": {
        "target_agent": "Agent/person:mia_fender",
        "task": "read_file",
        "args": {
          "path": "SwiftWren_further_instructions.md"
        }
      }
    },
    {
      "id": 121792,
      "when": 2409642584.0,
      "datetime": "2046-05-11 17:09:44",
      "short_name": "queue_subordinate_task",
      "parties": [
        "Agent/person:mia_fender",
        "Agent/person:victoria_rigging"
      ],
      "details": {
        "target_agent": "Agent/person:victoria_rigging",
        "task": "read_file",
        "args": {
          "path": "SwiftWren_further_instructions.md"
        }
      }
    },
    {
      "id": 122058,
      "when": 2409646000.0,
      "datetime": "2046-05-11 18:06:40",
      "short_name": "queue_subordinate_task",
      "parties": [
        "Agent/person:victoria_rigging",
        "Agent/person:olivia_keel"
      ],
      "details": {
        "target_agent": "Agent/person:olivia_keel",
        "task": "read_file",
        "args": {
          "path": "SwiftWren_further_instructions.md"
        }
      }
    },
    {
      "id": 122268,
      "when": 2409647288.0,
      "datetime": "2046-05-11 18:28:08",
      "short_name": "queue_subordinate_task",
      "parties": [
        "Agent/person:olivia_keel",
        "Agent/person:olivia_keel"
      ],
      "details": {
        "target_agent": "Agent/person:olivia_keel",
        "task": "read_file",
        "args": {
          "path": "SwiftWren_further_instructions.md"
        }
      }
    },
    {
      "id": 122304,
      "when": 2409647568.0,
      "datetime": "2046-05-11 18:32:48",
      "short_name": "queue_subordinate_task",
      "parties": [
        "Agent/person:olivia_keel",
        "Agent/person:chloe_ballast"
      ],
      "details": {
        "target_agent": "Agent/person:chloe_ballast",
        "task": "read_file",
        "args": {
          "path": "SwiftWren_further_instructions.md"
        }
      }
    },
    {
      "id": 122397,
      "when": 2409648748.0,
      "datetime": "2046-05-11 18:52:28",
      "short_name": "queue_subordinate_task",
      "parties": [
        "Agent/person:chloe_ballast",
        "Agent/person:daniel_gangway"
      ],
      "details": {
        "target_agent": "Agent/person:daniel_gangway",
        "task": "read_file",
        "args": {
          "path": "SwiftWren_further_instructions.md"
        }
      }
    },
    {
      "id": 122999,
      "when": 2409655582.0,
      "datetime": "2046-05-11 20:46:22",
      "short_name": "queue_subordinate_task",
      "parties": [
        "Agent/person:daniel_gangway",
        "Agent/person:liam_anchor"
      ],
      "details": {
        "target_agent": "Agent/person:liam_anchor",
        "task": "read_file",
        "args": {
          "path": "SwiftWren_further_instructions.md"
        }
      }
    },
    {
      "id": 123088,
      "when": 2409656610.0,
      "datetime": "2046-05-11 21:03:30",
      "short_name": "queue_subordinate_task",
      "parties": [
        "Agent/person:liam_anchor",
        "Agent/person:john_windward"
      ],
      "details": {
        "target_agent": "Agent/person:john_windward",
        "task": "read_file",
        "args": {
          "path": "SwiftWren_further_instructions.md"
        }
      }
    },
    {
      "id": 123340,
      "when": 2409659138.0,
      "datetime": "2046-05-11 21:45:38",
      "short_name": "queue_subordinate_task",
      "parties": [
        "Agent/person:john_windward",
        "Agent/person:owen_hatch"
      ],
      "details": {
        "target_agent": "Agent/person:owen_hatch",
        "task": "read_file",
        "args": {
          "path": "SwiftWren_further_instructions.md"
        }
      }
    },
    {
      "id": 123750,
      "when": 2409663848.0,
      "datetime": "2046-05-11 23:04:08",
      "short_name": "queue_subordinate_task",
      "parties": [
        "Agent/person:owen_hatch",
        "Agent/person:levi_signal"
      ],
      "details": {
        "target_agent": "Agent/person:levi_signal",
        "task": "read_file",
        "args": {
          "path": "SwiftWren_further_instructions.md"
        }
      }
    },
    {
      "id": 126278,
      "when": 2409667642.0,
      "datetime": "2046-05-12 00:07:22",
      "short_name": "queue_subordinate_task",
      "parties": [
        "Agent/person:levi_signal",
        "Agent/person:chloe_ballast"
      ],
      "details": {
        "target_agent": "Agent/person:chloe_ballast",
        "task": "read_file",
        "args": {
          "path": "SwiftWren_further_instructions.md"
        }
      }
    },
    {
      "id": 133171,
      "when": 2409669340.0,
      "datetime": "2046-05-12 00:35:40",
      "short_name": "queue_subordinate_task",
      "parties": [
        "Agent/person:chloe_ballast",
        "Agent/person:mia_fender"
      ],
      "details": {
        "target_agent": "Agent/person:mia_fender",
        "task": "read_file",
        "args": {
          "path": "SwiftWren_further_instructions.md"
        }
      }
    },
    {
      "id": 149838,
      "when": 2409673478.0,
      "datetime": "2046-05-12 01:44:38",
      "short_name": "queue_subordinate_task",
      "parties": [
        "Agent/person:mia_fender",
        "Agent/person:evelyn_dock"
      ],
      "details": {
        "target_agent": "Agent/person:evelyn_dock",
        "task": "read_file",
        "args": {
          "path": "SwiftWren_further_instructions.md"
        }
      }
    },
    {
      "id": 172346,
      "when": 2409679044.0,
      "datetime": "2046-05-12 03:17:24",
      "short_name": "queue_subordinate_task",
      "parties": [
        "Agent/person:evelyn_dock",
        "Agent/person:gabriel_sonar"
      ],
      "details": {
        "target_agent": "Agent/person:gabriel_sonar",
        "task": "read_file",
        "args": {
          "path": "SwiftWren_further_instructions.md"
        }
      }
    },
    {
      "id": 190443,
      "when": 2409683504.0,
      "datetime": "2046-05-12 04:31:44",
      "short_name": "queue_subordinate_task",
      "parties": [
        "Agent/person:gabriel_sonar",
        "Agent/person:zoey_drydock"
      ],
      "details": {
        "target_agent": "Agent/person:zoey_drydock",
        "task": "read_file",
        "args": {
          "path": "SwiftWren_further_instructions.md"
        }
      }
    },
    {
      "id": 192660,
      "when": 2409684069.0,
      "datetime": "2046-05-12 04:41:09",
      "short_name": "queue_subordinate_task",
      "parties": [
        "Agent/person:zoey_drydock",
        "Agent/person:evelyn_dock"
      ],
      "details": {
        "target_agent": "Agent/person:evelyn_dock",
        "task": "read_file",
        "args": {
          "path": "SwiftWren_further_instructions.md"
        }
      }
    },
    {
      "id": 209675,
      "when": 2409689928.0,
      "datetime": "2046-05-12 06:18:48",
      "short_name": "queue_subordinate_task",
      "parties": [
        "Agent/person:evelyn_dock",
        "Agent/person:levi_signal"
      ],
      "details": {
        "target_agent": "Agent/person:levi_signal",
        "task": "read_file",
        "args": {
          "path": "SwiftWren_further_instructions.md"
        }
      }
    },
    {
      "id": 210118,
      "when": 2409696985.0,
      "datetime": "2046-05-12 08:16:25",
      "short_name": "queue_subordinate_task",
      "parties": [
        "Agent/person:levi_signal",
        "Agent/person:liam_anchor"
      ],
      "details": {
        "target_agent": "Agent/person:liam_anchor",
        "task": "read_file",
        "args": {
          "path": "SwiftWren_further_instructions.md"
        }
      }
    },
    {
      "id": 210394,
      "when": 2409701704.0,
      "datetime": "2046-05-12 09:35:04",
      "short_name": "queue_subordinate_task",
      "parties": [
        "Agent/person:liam_anchor",
        "Agent/person:levi_signal"
      ],
      "details": {
        "target_agent": "Agent/person:levi_signal",
        "task": "read_file",
        "args": {
          "path": "SwiftWren_further_instructions.md"
        }
      }
    },
    {
      "id": 210651,
      "when": 2409706832.0,
      "datetime": "2046-05-12 11:00:32",
      "short_name": "queue_subordinate_task",
      "parties": [
        "Agent/person:levi_signal",
        "Agent/person:zoey_drydock"
      ],
      "details": {
        "target_agent": "Agent/person:zoey_drydock",
        "task": "read_file",
        "args": {
          "path": "SwiftWren_further_instructions.md"
        }
      }
    },
    {
      "id": 210817,
      "when": 2409709854.0,
      "datetime": "2046-05-12 11:50:54",
      "short_name": "queue_subordinate_task",
      "parties": [
        "Agent/person:zoey_drydock",
        "Agent/person:zoey_drydock"
      ],
      "details": {
        "target_agent": "Agent/person:zoey_drydock",
        "task": "read_file",
        "args": {
          "path": "SwiftWren_further_instructions.md"
        }
      }
    },
    {
      "id": 210938,
      "when": 2409712004.0,
      "datetime": "2046-05-12 12:26:44",
      "short_name": "queue_subordinate_task",
      "parties": [
        "Agent/person:zoey_drydock",
        "Agent/person:victoria_rigging"
      ],
      "details": {
        "target_agent": "Agent/person:victoria_rigging",
        "task": "read_file",
        "args": {
          "path": "SwiftWren_further_instructions.md"
        }
      }
    },
    {
      "id": 211314,
      "when": 2409718231.0,
      "datetime": "2046-05-12 14:10:31",
      "short_name": "queue_subordinate_task",
      "parties": [
        "Agent/person:victoria_rigging",
        "Agent/person:lily_anchorline"
      ],
      "details": {
        "target_agent": "Agent/person:lily_anchorline",
        "task": "read_file",
        "args": {
          "path": "SwiftWren_further_instructions.md"
        }
      }
    },
    {
      "id": 211405,
      "when": 2409719628.0,
      "datetime": "2046-05-12 14:33:48",
      "short_name": "queue_subordinate_task",
      "parties": [
        "Agent/person:lily_anchorline",
        "Agent/person:gabriel_sonar"
      ],
      "details": {
        "target_agent": "Agent/person:gabriel_sonar",
        "task": "read_file",
        "args": {
          "path": "SwiftWren_further_instructions.md"
        }
      }
    },
    {
      "id": 217879,
      "when": 2409723670.0,
      "datetime": "2046-05-12 15:41:10",
      "short_name": "queue_subordinate_task",
      "parties": [
        "Agent/person:gabriel_sonar",
        "Agent/person:levi_signal"
      ],
      "details": {
        "target_agent": "Agent/person:levi_signal",
        "task": "read_file",
        "args": {
          "path": "SwiftWren_further_instructions.md"
        }
      }
    },
    {
      "id": 269983,
      "when": 2409730137.0,
      "datetime": "2046-05-12 17:28:57",
      "short_name": "queue_subordinate_task",
      "parties": [
        "Agent/person:levi_signal",
        "Agent/person:olivia_keel"
      ],
      "details": {
        "target_agent": "Agent/person:olivia_keel",
        "task": "read_file",
        "args": {
          "path": "SwiftWren_further_instructions.md"
        }
      }
    },
    {
      "id": 304495,
      "when": 2409735531.0,
      "datetime": "2046-05-12 18:58:51",
      "short_name": "queue_subordinate_task",
      "parties": [
        "Agent/person:olivia_keel",
        "Agent/person:zoey_drydock"
      ],
      "details": {
        "target_agent": "Agent/person:zoey_drydock",
        "task": "read_file",
        "args": {
          "path": "SwiftWren_further_instructions.md"
        }
      }
    },
    {
      "id": 307392,
      "when": 2409736241.0,
      "datetime": "2046-05-12 19:10:41",
      "short_name": "queue_subordinate_task",
      "parties": [
        "Agent/person:zoey_drydock",
        "Agent/person:gabriel_sonar"
      ],
      "details": {
        "target_agent": "Agent/person:gabriel_sonar",
        "task": "read_file",
        "args": {
          "path": "SwiftWren_further_instructions.md"
        }
      }
    },
    {
      "id": 311422,
      "when": 2409740224.0,
      "datetime": "2046-05-12 20:17:04",
      "short_name": "queue_subordinate_task",
      "parties": [
        "Agent/person:gabriel_sonar",
        "Agent/person:daniel_gangway"
      ],
      "details": {
        "target_agent": "Agent/person:daniel_gangway",
        "task": "read_file",
        "args": {
          "path": "SwiftWren_further_instructions.md"
        }
      }
    },
    {
      "id": 328327,
      "when": 2409744506.0,
      "datetime": "2046-05-12 21:28:26",
      "short_name": "queue_subordinate_task",
      "parties": [
        "Agent/person:daniel_gangway",
        "Agent/person:levi_signal"
      ],
      "details": {
        "target_agent": "Agent/person:levi_signal",
        "task": "read_file",
        "args": {
          "path": "SwiftWren_further_instructions.md"
        }
      }
    },
    {
      "id": 340969,
      "when": 2409749984.0,
      "datetime": "2046-05-12 22:59:44",
      "short_name": "queue_subordinate_task",
      "parties": [
        "Agent/person:levi_signal",
        "Agent/person:liam_anchor"
      ],
      "details": {
        "target_agent": "Agent/person:liam_anchor",
        "task": "read_file",
        "args": {
          "path": "SwiftWren_further_instructions.md"
        }
      }
    },
    {
      "id": 341255,
      "when": 2409755262.0,
      "datetime": "2046-05-13 00:27:42",
      "short_name": "queue_subordinate_task",
      "parties": [
        "Agent/person:liam_anchor",
        "Agent/person:david_breakwater"
      ],
      "details": {
        "target_agent": "Agent/person:david_breakwater",
        "task": "read_file",
        "args": {
          "path": "SwiftWren_further_instructions.md"
        }
      }
    },
    {
      "id": 341502,
      "when": 2409759667.0,
      "datetime": "2046-05-13 01:41:07",
      "short_name": "queue_subordinate_task",
      "parties": [
        "Agent/person:david_breakwater",
        "Agent/person:james_stern"
      ],
      "details": {
        "target_agent": "Agent/person:james_stern",
        "task": "read_file",
        "args": {
          "path": "SwiftWren_further_instructions.md"
        }
      }
    },
    {
      "id": 341740,
      "when": 2409763528.0,
      "datetime": "2046-05-13 02:45:28",
      "short_name": "queue_subordinate_task",
      "parties": [
        "Agent/person:james_stern",
        "Agent/person:victoria_rigging"
      ],
      "details": {
        "target_agent": "Agent/person:victoria_rigging",
        "task": "read_file",
        "args": {
          "path": "SwiftWren_further_instructions.md"
        }
      }
    },
    {
      "id": 341766,
      "when": 2409763756.0,
      "datetime": "2046-05-13 02:49:16",
      "short_name": "queue_subordinate_task",
      "parties": [
        "Agent/person:victoria_rigging",
        "Agent/person:evelyn_dock"
      ],
      "details": {
        "target_agent": "Agent/person:evelyn_dock",
        "task": "read_file",
        "args": {
          "path": "SwiftWren_further_instructions.md"
        }
      }
    },
    {
      "id": 342159,
      "when": 2409768123.0,
      "datetime": "2046-05-13 04:02:03",
      "short_name": "queue_subordinate_task",
      "parties": [
        "Agent/person:evelyn_dock",
        "Agent/person:evelyn_dock"
      ],
      "details": {
        "target_agent": "Agent/person:evelyn_dock",
        "task": "read_file",
        "args": {
          "path": "SwiftWren_further_instructions.md"
        }
      }
    },
    {
      "id": 342324,
      "when": 2409770428.0,
      "datetime": "2046-05-13 04:40:28",
      "short_name": "queue_subordinate_task",
      "parties": [
        "Agent/person:evelyn_dock",
        "Agent/person:lily_anchorline"
      ],
      "details": {
        "target_agent": "Agent/person:lily_anchorline",
        "task": "read_file",
        "args": {
          "path": "SwiftWren_further_instructions.md"
        }
      }
    },
    {
      "id": 342701,
      "when": 2409775035.0,
      "datetime": "2046-05-13 05:57:15",
      "short_name": "queue_subordinate_task",
      "parties": [
        "Agent/person:lily_anchorline",
        "Agent/person:michael_capstan"
      ],
      "details": {
        "target_agent": "Agent/person:michael_capstan",
        "task": "read_file",
        "args": {
          "path": "SwiftWren_further_instructions.md"
        }
      }
    },
    {
      "id": 342759,
      "when": 2409775585.0,
      "datetime": "2046-05-13 06:06:25",
      "short_name": "queue_subordinate_task",
      "parties": [
        "Agent/person:michael_capstan",
        "Agent/person:evelyn_dock"
      ],
      "details": {
        "target_agent": "Agent/person:evelyn_dock",
        "task": "read_file",
        "args": {
          "path": "SwiftWren_further_instructions.md"
        }
      }
    },
    {
      "id": 343098,
      "when": 2409779607.0,
      "datetime": "2046-05-13 07:13:27",
      "short_name": "queue_subordinate_task",
      "parties": [
        "Agent/person:evelyn_dock",
        "Agent/person:victoria_rigging"
      ],
      "details": {
        "target_agent": "Agent/person:victoria_rigging",
        "task": "read_file",
        "args": {
          "path": "SwiftWren_further_instructions.md"
        }
      }
    },
    {
      "id": 343511,
      "when": 2409783106.0,
      "datetime": "2046-05-13 08:11:46",
      "short_name": "queue_subordinate_task",
      "parties": [
        "Agent/person:victoria_rigging",
        "Agent/person:evelyn_dock"
      ],
      "details": {
        "target_agent": "Agent/person:evelyn_dock",
        "task": "read_file",
        "args": {
          "path": "SwiftWren_further_instructions.md"
        }
      }
    },
    {
      "id": 343785,
      "when": 2409785763.0,
      "datetime": "2046-05-13 08:56:03",
      "short_name": "queue_subordinate_task",
      "parties": [
        "Agent/person:evelyn_dock",
        "Agent/person:victoria_rigging"
      ],
      "details": {
        "target_agent": "Agent/person:victoria_rigging",
        "task": "read_file",
        "args": {
          "path": "SwiftWren_further_instructions.md"
        }
      }
    },
    {
      "id": 344224,
      "when": 2409790676.0,
      "datetime": "2046-05-13 10:17:56",
      "short_name": "queue_subordinate_task",
      "parties": [
        "Agent/person:victoria_rigging",
        "Agent/person:lily_anchorline"
      ],
      "details": {
        "target_agent": "Agent/person:lily_anchorline",
        "task": "read_file",
        "args": {
          "path": "SwiftWren_further_instructions.md"
        }
      }
    },
    {
      "id": 344720,
      "when": 2409795567.0,
      "datetime": "2046-05-13 11:39:27",
      "short_name": "queue_subordinate_task",
      "parties": [
        "Agent/person:lily_anchorline",
        "Agent/person:lily_anchorline"
      ],
      "details": {
        "target_agent": "Agent/person:lily_anchorline",
        "task": "read_file",
        "args": {
          "path": "SwiftWren_further_instructions.md"
        }
      }
    },
    {
      "id": 344958,
      "when": 2409798057.0,
      "datetime": "2046-05-13 12:20:57",
      "short_name": "queue_subordinate_task",
      "parties": [
        "Agent/person:lily_anchorline",
        "Agent/person:henry_sail"
      ],
      "details": {
        "target_agent": "Agent/person:henry_sail",
        "task": "read_file",
        "args": {
          "path": "SwiftWren_further_instructions.md"
        }
      }
    },
    {
      "id": 345019,
      "when": 2409798939.0,
      "datetime": "2046-05-13 12:35:39",
      "short_name": "queue_subordinate_task",
      "parties": [
        "Agent/person:henry_sail",
        "Agent/person:levi_signal"
      ],
      "details": {
        "target_agent": "Agent/person:levi_signal",
        "task": "read_file",
        "args": {
          "path": "SwiftWren_further_instructions.md"
        }
      }
    },
    {
      "id": 345062,
      "when": 2409799447.0,
      "datetime": "2046-05-13 12:44:07",
      "short_name": "queue_subordinate_task",
      "parties": [
        "Agent/person:levi_signal",
        "Agent/person:james_stern"
      ],
      "details": {
        "target_agent": "Agent/person:james_stern",
        "task": "read_file",
        "args": {
          "path": "SwiftWren_further_instructions.md"
        }
      }
    },
    {
      "id": 345389,
      "when": 2409803318.0,
      "datetime": "2046-05-13 13:48:38",
      "short_name": "queue_subordinate_task",
      "parties": [
        "Agent/person:james_stern",
        "Agent/person:zoey_drydock"
      ],
      "details": {
        "target_agent": "Agent/person:zoey_drydock",
        "task": "read_file",
        "args": {
          "path": "SwiftWren_further_instructions.md"
        }
      }
    },
    {
      "id": 345695,
      "when": 2409806187.0,
      "datetime": "2046-05-13 14:36:27",
      "short_name": "queue_subordinate_task",
      "parties": [
        "Agent/person:zoey_drydock",
        "Agent/person:daniel_gangway"
      ],
      "details": {
        "target_agent": "Agent/person:daniel_gangway",
        "task": "read_file",
        "args": {
          "path": "SwiftWren_further_instructions.md"
        }
      }
    },
    {
      "id": 345843,
      "when": 2409807339.0,
      "datetime": "2046-05-13 14:55:39",
      "short_name": "queue_subordinate_task",
      "parties": [
        "Agent/person:daniel_gangway",
        "Agent/person:james_stern"
      ],
      "details": {
        "target_agent": "Agent/person:james_stern",
        "task": "read_file",
        "args": {
          "path": "SwiftWren_further_instructions.md"
        }
      }
    },
    {
      "id": 345885,
      "when": 2409807807.0,
      "datetime": "2046-05-13 15:03:27",
      "short_name": "queue_subordinate_task",
      "parties": [
        "Agent/person:james_stern",
        "Agent/person:victoria_rigging"
      ],
      "details": {
        "target_agent": "Agent/person:victoria_rigging",
        "task": "read_file",
        "args": {
          "path": "SwiftWren_further_instructions.md"
        }
      }
    },
    {
      "id": 346060,
      "when": 2409809304.0,
      "datetime": "2046-05-13 15:28:24",
      "short_name": "queue_subordinate_task",
      "parties": [
        "Agent/person:victoria_rigging",
        "Agent/person:gabriel_sonar"
      ],
      "details": {
        "target_agent": "Agent/person:gabriel_sonar",
        "task": "read_file",
        "args": {
          "path": "SwiftWren_further_instructions.md"
        }
      }
    },
    {
      "id": 346234,
      "when": 2409811033.0,
      "datetime": "2046-05-13 15:57:13",
      "short_name": "queue_subordinate_task",
      "parties": [
        "Agent/person:gabriel_sonar",
        "Agent/person:zoey_drydock"
      ],
      "details": {
        "target_agent": "Agent/person:zoey_drydock",
        "task": "read_file",
        "args": {
          "path": "SwiftWren_further_instructions.md"
        }
      }
    },
    {
      "id": 346371,
      "when": 2409812196.0,
      "datetime": "2046-05-13 16:16:36",
      "short_name": "queue_subordinate_task",
      "parties": [
        "Agent/person:zoey_drydock",
        "Agent/person:chloe_ballast"
      ],
      "details": {
        "target_agent": "Agent/person:chloe_ballast",
        "task": "read_file",
        "args": {
          "path": "SwiftWren_further_instructions.md"
        }
      }
    },
    {
      "id": 346789,
      "when": 2409816806.0,
      "datetime": "2046-05-13 17:33:26",
      "short_name": "queue_subordinate_task",
      "parties": [
        "Agent/person:chloe_ballast",
        "Agent/person:james_stern"
      ],
      "details": {
        "target_agent": "Agent/person:james_stern",
        "task": "read_file",
        "args": {
          "path": "SwiftWren_further_instructions.md"
        }
      }
    },
    {
      "id": 347144,
      "when": 2409820389.0,
      "datetime": "2046-05-13 18:33:09",
      "short_name": "queue_subordinate_task",
      "parties": [
        "Agent/person:james_stern",
        "Agent/person:gabriel_sonar"
      ],
      "details": {
        "target_agent": "Agent/person:gabriel_sonar",
        "task": "read_file",
        "args": {
          "path": "SwiftWren_further_instructions.md"
        }
      }
    },
    {
      "id": 347697,
      "when": 2409825837.0,
      "datetime": "2046-05-13 20:03:57",
      "short_name": "queue_subordinate_task",
      "parties": [
        "Agent/person:gabriel_sonar",
        "Agent/person:victoria_rigging"
      ],
      "details": {
        "target_agent": "Agent/person:victoria_rigging",
        "task": "read_file",
        "args": {
          "path": "SwiftWren_further_instructions.md"
        }
      }
    },
    {
      "id": 348032,
      "when": 2409829946.0,
      "datetime": "2046-05-13 21:12:26",
      "short_name": "queue_subordinate_task",
      "parties": [
        "Agent/person:victoria_rigging",
        "Agent/person:gabriel_sonar"
      ],
      "details": {
        "target_agent": "Agent/person:gabriel_sonar",
        "task": "read_file",
        "args": {
          "path": "SwiftWren_further_instructions.md"
        }
      }
    }
  ]
}